LICENCE
MANIFEST.in
README.md
setup.py
overly/__init__.py
overly/base.py
overly/constants.py
overly/default_server_cert.pem
overly/default_server_key.pem
overly/errors.py
overly/http_utils.py
overly/socket_utils.py
overly/steps.py
overly.egg-info/PKG-INFO
overly.egg-info/SOURCES.txt
overly.egg-info/dependency_links.txt
overly.egg-info/requires.txt
overly.egg-info/top_level.txt